pyNutFiles/__init__.py
pyNutFiles/_lib.py
pyNutFiles/nutFiles.py
pynut_Files-3.1.1.dist-info/LICENSE
pynut_Files-3.1.1.dist-info/METADATA
pynut_Files-3.1.1.dist-info/WHEEL
pynut_Files-3.1.1.dist-info/top_level.txt
pynut_Files-3.1.1.dist-info/RECORD
