Metadata-Version: 2.1
Name: pynut-Files
Version: 3.1.1
Summary: Function easing life :)
Home-page: https://github.com/Laurent-Tupin/pynut_Files
Author: Laurent Tupin
Author-email: laurent.tupinn@gmail.com
License: Copyright 2022-2035
Platform: UNKNOWN
Classifier: License :: Free For Home Use
Classifier: Programming Language :: Python :: 3
Classifier: Programming Language :: Python :: 3.9
License-File: LICENSE
Requires-Dist: pynut-tools (==3.1.1)
Requires-Dist: openpyxl (==3.1.0)
Requires-Dist: psutil (==5.9.4)
Requires-Dist: pywin32 (==305)
Requires-Dist: xlrd (==2.0.1)
Requires-Dist: XlsxWriter (==1.4.5)
Requires-Dist: xlwings (==0.29.1)
